{
  "generatedAt": 1784062690,
  "gainers": [
    {
      "symbol": "SKHY",
      "shortName": "SK hynix Inc. - American Depos",
      "price": 193.92,
      "changePct": 27.28585,
      "change": 41.569992,
      "volume": 68533119,
      "marketCap": 1376550518784
    },
    {
      "symbol": "CHRN",
      "shortName": "ChronoScale Holdings Corporatio",
      "price": 23.01,
      "changePct": 16.683575,
      "change": 3.290001,
      "volume": 329176,
      "marketCap": 3341393408
    },
    {
      "symbol": "AXTI",
      "shortName": "AXT Inc",
      "price": 57.57,
      "changePct": 14.090369,
      "change": 7.1100006,
      "volume": 10231568,
      "marketCap": 3766412800
    },
    {
      "symbol": "ATAI",
      "shortName": "AtaiBeckley Inc.",
      "price": 5.67,
      "changePct": 14.084514,
      "change": 0.7000003,
      "volume": 11749843,
      "marketCap": 2087505152
    },
    {
      "symbol": "SEZL",
      "shortName": "Sezzle Inc.",
      "price": 182.39,
      "changePct": 13.815912,
      "change": 22.14,
      "volume": 741002,
      "marketCap": 6133232128
    },
    {
      "symbol": "TGB",
      "shortName": "Trekor Metals Limited",
      "price": 7.97,
      "changePct": 13.5328,
      "change": 0.95,
      "volume": 5758195,
      "marketCap": 2914209024
    },
    {
      "symbol": "CRWD",
      "shortName": "CrowdStrike Holdings, Inc.",
      "price": 210.73,
      "changePct": 12.144108,
      "change": 22.819992,
      "volume": 11636383,
      "marketCap": 214577774592
    },
    {
      "symbol": "AAOI",
      "shortName": "Applied Optoelectronics, Inc.",
      "price": 125.45,
      "changePct": 12.129066,
      "change": 13.57,
      "volume": 9888238,
      "marketCap": 10066454528
    },
    {
      "symbol": "RGC",
      "shortName": "Regencell Bioscience Holdings L",
      "price": 5.65,
      "changePct": 11.8811865,
      "change": 0.5999999,
      "volume": 448418,
      "marketCap": 2793862400
    },
    {
      "symbol": "BMNR",
      "shortName": "BitMine Immersion Technologies,",
      "price": 16.29,
      "changePct": 11.499,
      "change": 1.68,
      "volume": 43447439,
      "marketCap": 9278406656
    },
    {
      "symbol": "NTSK",
      "shortName": "Netskope, Inc.",
      "price": 14.27,
      "changePct": 11.484377,
      "change": 1.4700003,
      "volume": 9463807,
      "marketCap": 5763990528
    },
    {
      "symbol": "TSEM",
      "shortName": "Tower Semiconductor Ltd.",
      "price": 255.49,
      "changePct": 11.23738,
      "change": 25.810013,
      "volume": 4631174,
      "marketCap": 28878352384
    },
    {
      "symbol": "YSS",
      "shortName": "York Space Systems Inc.",
      "price": 21.26,
      "changePct": 11.1343,
      "change": 2.13,
      "volume": 1448980,
      "marketCap": 2793522176
    },
    {
      "symbol": "OKTA",
      "shortName": "Okta, Inc.",
      "price": 154.62,
      "changePct": 10.814877,
      "change": 15.089996,
      "volume": 4517498,
      "marketCap": 26874093568
    },
    {
      "symbol": "TXG",
      "shortName": "10x Genomics, Inc.",
      "price": 45.79,
      "changePct": 9.624133,
      "change": 4.0200005,
      "volume": 3832719,
      "marketCap": 5813324288
    },
    {
      "symbol": "COAG",
      "shortName": "Hemab Therapeutics Holdings, In",
      "price": 43.31,
      "changePct": 9.617826,
      "change": 3.800003,
      "volume": 321616,
      "marketCap": 2022811264
    },
    {
      "symbol": "CAMT",
      "shortName": "Camtek Ltd.",
      "price": 149.9,
      "changePct": 9.592042,
      "change": 13.119995,
      "volume": 686811,
      "marketCap": 6993811968
    },
    {
      "symbol": "GS",
      "shortName": "Goldman Sachs Group, Inc. (The)",
      "price": 1140.0,
      "changePct": 8.99599,
      "change": 94.09,
      "volume": 3237929,
      "marketCap": 336308469760
    },
    {
      "symbol": "ERAS",
      "shortName": "Erasca, Inc.",
      "price": 19.5,
      "changePct": 8.938549,
      "change": 1.6000004,
      "volume": 10425876,
      "marketCap": 6064198656
    },
    {
      "symbol": "CLSK",
      "shortName": "CleanSpark, Inc.",
      "price": 13.45,
      "changePct": 8.818771,
      "change": 1.0900002,
      "volume": 75483451,
      "marketCap": 3451385856
    },
    {
      "symbol": "ENLT",
      "shortName": "Enlight Renewable Energy Ltd.",
      "price": 90.25,
      "changePct": 8.813598,
      "change": 7.3099976,
      "volume": 303138,
      "marketCap": 12617629696
    },
    {
      "symbol": "TENB",
      "shortName": "Tenable Holdings, Inc.",
      "price": 42.65,
      "changePct": 8.801023,
      "change": 3.4500008,
      "volume": 4819591,
      "marketCap": 4703099904
    },
    {
      "symbol": "BLSH",
      "shortName": "Bullish",
      "price": 24.85,
      "changePct": 8.65763,
      "change": 1.98,
      "volume": 1448555,
      "marketCap": 3768461568
    },
    {
      "symbol": "SAIL",
      "shortName": "SailPoint, Inc.",
      "price": 15.2,
      "changePct": 8.49393,
      "change": 1.1899996,
      "volume": 6358163,
      "marketCap": 8621180928
    },
    {
      "symbol": "TRVI",
      "shortName": "Trevi Therapeutics, Inc.",
      "price": 17.91,
      "changePct": 8.41404,
      "change": 1.3899994,
      "volume": 2488803,
      "marketCap": 2542856704
    }
  ],
  "losers": [
    {
      "symbol": "IBM",
      "shortName": "International Business Machines",
      "price": 217.07,
      "changePct": -25.2076,
      "change": -73.16,
      "volume": 66683527,
      "marketCap": 204020908032
    },
    {
      "symbol": "PSNY",
      "shortName": "Polestar Automotive Holding UK ",
      "price": 15.31,
      "changePct": -14.99167,
      "change": -2.6999998,
      "volume": 377991,
      "marketCap": 2218479360
    },
    {
      "symbol": "DNLI",
      "shortName": "Denali Therapeutics Inc.",
      "price": 22.65,
      "changePct": -14.463747,
      "change": -3.83,
      "volume": 5742302,
      "marketCap": 3594775552
    },
    {
      "symbol": "ERIC",
      "shortName": "Ericsson",
      "price": 10.14,
      "changePct": -13.481228,
      "change": -1.5799999,
      "volume": 39311170,
      "marketCap": 33479731200
    },
    {
      "symbol": "BIIB",
      "shortName": "Biogen Inc.",
      "price": 191.95,
      "changePct": -8.171077,
      "change": -17.080002,
      "volume": 3898997,
      "marketCap": 28338944000
    },
    {
      "symbol": "VIRT",
      "shortName": "Virtu Financial, Inc.",
      "price": 59.57,
      "changePct": -7.88619,
      "change": -5.1,
      "volume": 1921011,
      "marketCap": 12818159616
    },
    {
      "symbol": "NBIS",
      "shortName": "Nebius Group N.V.",
      "price": 194.09,
      "changePct": -7.8001037,
      "change": -16.419998,
      "volume": 17379284,
      "marketCap": 49279098880
    },
    {
      "symbol": "TDC",
      "shortName": "Teradata Corporation",
      "price": 31.42,
      "changePct": -7.47938,
      "change": -2.54,
      "volume": 4916344,
      "marketCap": 2956622080
    },
    {
      "symbol": "FRHC",
      "shortName": "Freedom Holding Corp.",
      "price": 148.91,
      "changePct": -7.4057975,
      "change": -11.910004,
      "volume": 210748,
      "marketCap": 9480643584
    },
    {
      "symbol": "TEAM",
      "shortName": "Atlassian Corporation",
      "price": 89.08,
      "changePct": -7.36273,
      "change": -7.080002,
      "volume": 4277501,
      "marketCap": 22605641728
    },
    {
      "symbol": "WULF",
      "shortName": "TeraWulf Inc.",
      "price": 19.41,
      "changePct": -7.0847273,
      "change": -1.4799995,
      "volume": 57656321,
      "marketCap": 9618288640
    },
    {
      "symbol": "HCA",
      "shortName": "HCA Healthcare, Inc.",
      "price": 363.6,
      "changePct": -6.94579,
      "change": -27.14,
      "volume": 3893129,
      "marketCap": 80660955136
    },
    {
      "symbol": "ISRG",
      "shortName": "Intuitive Surgical, Inc.",
      "price": 379.5,
      "changePct": -6.7842393,
      "change": -27.619995,
      "volume": 5668144,
      "marketCap": 134404800512
    },
    {
      "symbol": "IMOS",
      "shortName": "ChipMOS TECHNOLOGIES INC.",
      "price": 64.47,
      "changePct": -6.754409,
      "change": -4.669998,
      "volume": 143966,
      "marketCap": 2241680128
    },
    {
      "symbol": "KRYS",
      "shortName": "Krystal Biotech, Inc.",
      "price": 339.43,
      "changePct": -6.6063204,
      "change": -24.01001,
      "volume": 498761,
      "marketCap": 10006312960
    },
    {
      "symbol": "MMED",
      "shortName": "MiniMed Group, Inc.",
      "price": 15.04,
      "changePct": -6.5838532,
      "change": -1.0600004,
      "volume": 953213,
      "marketCap": 4223876352
    },
    {
      "symbol": "KC",
      "shortName": "Kingsoft Cloud Holdings Limited",
      "price": 9.73,
      "changePct": -6.3522696,
      "change": -0.6600008,
      "volume": 2118420,
      "marketCap": 2912866816
    },
    {
      "symbol": "MZTI",
      "shortName": "The Marzetti Company",
      "price": 106.96,
      "changePct": -6.2658854,
      "change": -7.1500015,
      "volume": 405595,
      "marketCap": 2933097728
    },
    {
      "symbol": "CRUS",
      "shortName": "Cirrus Logic, Inc.",
      "price": 137.36,
      "changePct": -6.2453036,
      "change": -9.149994,
      "volume": 963407,
      "marketCap": 6930185728
    },
    {
      "symbol": "SYK",
      "shortName": "Stryker Corporation",
      "price": 311.07,
      "changePct": -6.14874,
      "change": -20.38,
      "volume": 4034180,
      "marketCap": 119252033536
    },
    {
      "symbol": "ARM",
      "shortName": "Arm Holdings plc",
      "price": 281.17,
      "changePct": -5.960058,
      "change": -17.819977,
      "volume": 8314663,
      "marketCap": 300311740416
    },
    {
      "symbol": "PSO",
      "shortName": "Pearson, Plc",
      "price": 16.57,
      "changePct": -5.90574,
      "change": -1.04,
      "volume": 2895413,
      "marketCap": 9948883968
    },
    {
      "symbol": "IT",
      "shortName": "Gartner, Inc.",
      "price": 132.97,
      "changePct": -5.90192,
      "change": -8.34,
      "volume": 1731540,
      "marketCap": 8902592512
    },
    {
      "symbol": "KD",
      "shortName": "Kyndryl Holdings, Inc.",
      "price": 11.61,
      "changePct": -5.76299,
      "change": -0.71,
      "volume": 5897340,
      "marketCap": 2560204800
    },
    {
      "symbol": "NOW",
      "shortName": "ServiceNow, Inc.",
      "price": 104.85,
      "changePct": -5.76128,
      "change": -6.41,
      "volume": 22825972,
      "marketCap": 108132646912
    }
  ],
  "actives": [
    {
      "symbol": "NU",
      "shortName": "Nu Holdings Ltd.",
      "price": 13.99,
      "changePct": 2.34089,
      "change": 0.32,
      "volume": 145644367,
      "marketCap": 67578478592
    },
    {
      "symbol": "AAL",
      "shortName": "American Airlines Group, Inc.",
      "price": 15.67,
      "changePct": -3.9239693,
      "change": -0.6399994,
      "volume": 136163907,
      "marketCap": 10363905024
    },
    {
      "symbol": "NVDA",
      "shortName": "NVIDIA Corporation",
      "price": 211.8,
      "changePct": 4.0641046,
      "change": 8.271606,
      "volume": 118014431,
      "marketCap": 5130007609344
    },
    {
      "symbol": "SKHYV",
      "shortName": "SK hynix Inc. - American Deposi",
      "price": 168.01,
      "changePct": 0.0,
      "change": 0.0,
      "volume": 107674661,
      "marketCap": 1192627142656
    },
    {
      "symbol": "ONDS",
      "shortName": "Ondas Inc",
      "price": 7.36,
      "changePct": 5.747128,
      "change": 0.4000001,
      "volume": 107332140,
      "marketCap": 4194012160
    },
    {
      "symbol": "OPEN",
      "shortName": "Opendoor Technologies Inc",
      "price": 4.55,
      "changePct": 1.4492766,
      "change": 0.06500006,
      "volume": 98083018,
      "marketCap": 4389552128
    },
    {
      "symbol": "INTC",
      "shortName": "Intel Corporation",
      "price": 107.76,
      "changePct": 4.4996114,
      "change": 4.6399994,
      "volume": 90554427,
      "marketCap": 541601759232
    },
    {
      "symbol": "SOFI",
      "shortName": "SoFi Technologies, Inc.",
      "price": 18.55,
      "changePct": 2.316603,
      "change": 0.42000008,
      "volume": 88638131,
      "marketCap": 23794849792
    },
    {
      "symbol": "PATH",
      "shortName": "UiPath, Inc.",
      "price": 11.94,
      "changePct": 0.759487,
      "change": 0.0899992,
      "volume": 83572383,
      "marketCap": 6186355712
    },
    {
      "symbol": "NOK",
      "shortName": "Nokia Corporation Sponsored",
      "price": 11.7,
      "changePct": 0.0855452,
      "change": 0.0100002,
      "volume": 82213777,
      "marketCap": 65315647488
    },
    {
      "symbol": "CLSK",
      "shortName": "CleanSpark, Inc.",
      "price": 13.45,
      "changePct": 8.818771,
      "change": 1.0900002,
      "volume": 75483451,
      "marketCap": 3451385856
    },
    {
      "symbol": "SKHY",
      "shortName": "SK hynix Inc. - American Depos",
      "price": 193.92,
      "changePct": 27.28585,
      "change": 41.569992,
      "volume": 68533119,
      "marketCap": 1376550518784
    },
    {
      "symbol": "IBM",
      "shortName": "International Business Machines",
      "price": 217.07,
      "changePct": -25.2076,
      "change": -73.16,
      "volume": 66683527,
      "marketCap": 204020908032
    },
    {
      "symbol": "WULF",
      "shortName": "TeraWulf Inc.",
      "price": 19.41,
      "changePct": -7.0847273,
      "change": -1.4799995,
      "volume": 57656321,
      "marketCap": 9618288640
    },
    {
      "symbol": "MARA",
      "shortName": "MARA Holdings, Inc.",
      "price": 12.16,
      "changePct": -0.24610117,
      "change": -0.029999733,
      "volume": 55787227,
      "marketCap": 4636249088
    },
    {
      "symbol": "PLTR",
      "shortName": "Palantir Technologies Inc.",
      "price": 133.72,
      "changePct": 2.8299046,
      "change": 3.680008,
      "volume": 49516261,
      "marketCap": 320568557568
    },
    {
      "symbol": "BAC",
      "shortName": "Bank of America Corporation",
      "price": 60.62,
      "changePct": 1.88235,
      "change": 1.12,
      "volume": 49159846,
      "marketCap": 430195343360
    },
    {
      "symbol": "JOBY",
      "shortName": "Joby Aviation, Inc.",
      "price": 7.89,
      "changePct": 5.48128,
      "change": 0.41,
      "volume": 46461445,
      "marketCap": 7760942080
    },
    {
      "symbol": "ORCL",
      "shortName": "Oracle Corporation",
      "price": 127.94,
      "changePct": -2.7368,
      "change": -3.59999,
      "volume": 45418183,
      "marketCap": 368527474688
    },
    {
      "symbol": "SPCX",
      "shortName": "Space Exploration Technologies ",
      "price": 136.08,
      "changePct": -2.199222,
      "change": -3.0599976,
      "volume": 45278731,
      "marketCap": 1792743440384
    },
    {
      "symbol": "T",
      "shortName": "AT&T Inc.",
      "price": 21.28,
      "changePct": -1.25289,
      "change": -0.269999,
      "volume": 44697826,
      "marketCap": 147860652032
    },
    {
      "symbol": "BMNR",
      "shortName": "BitMine Immersion Technologies,",
      "price": 16.29,
      "changePct": 11.499,
      "change": 1.68,
      "volume": 43447439,
      "marketCap": 9278406656
    },
    {
      "symbol": "PLUG",
      "shortName": "Plug Power, Inc.",
      "price": 2.27,
      "changePct": 4.60829,
      "change": 0.099999905,
      "volume": 42409247,
      "marketCap": 3166806784
    },
    {
      "symbol": "BBD",
      "shortName": "Banco Bradesco Sa",
      "price": 3.63,
      "changePct": 0.554023,
      "change": 0.0200002,
      "volume": 41732716,
      "marketCap": 38371684352
    },
    {
      "symbol": "ERIC",
      "shortName": "Ericsson",
      "price": 10.14,
      "changePct": -13.481228,
      "change": -1.5799999,
      "volume": 39311170,
      "marketCap": 33479731200
    }
  ]
}