{
  "generatedAt": 1784215004,
  "gainers": [
    {
      "symbol": "MAAS",
      "shortName": "Maase Inc.",
      "price": 22.19,
      "changePct": 34.2683,
      "change": 5.620001,
      "volume": 335857,
      "marketCap": 9811876864
    },
    {
      "symbol": "ATAI",
      "shortName": "AtaiBeckley Inc.",
      "price": 7.155,
      "changePct": 33.50131,
      "change": 1.7950001,
      "volume": 103771986,
      "marketCap": 2634232832
    },
    {
      "symbol": "MAN",
      "shortName": "ManpowerGroup",
      "price": 51.69,
      "changePct": 32.495502,
      "change": 12.669998,
      "volume": 2018773,
      "marketCap": 2403964672
    },
    {
      "symbol": "LCID",
      "shortName": "Lucid Group, Inc.",
      "price": 6.6994,
      "changePct": 12.607675,
      "change": 0.74940014,
      "volume": 17973305,
      "marketCap": 2614486272
    },
    {
      "symbol": "ABT",
      "shortName": "Abbott Laboratories",
      "price": 99.695,
      "changePct": 11.678059,
      "change": 10.425003,
      "volume": 13245390,
      "marketCap": 173650051072
    },
    {
      "symbol": "GHRS",
      "shortName": "GH Research PLC",
      "price": 29.88,
      "changePct": 10.995539,
      "change": 2.959999,
      "volume": 756812,
      "marketCap": 2050034432
    },
    {
      "symbol": "RHI",
      "shortName": "Robert Half Inc.",
      "price": 40.53,
      "changePct": 10.435962,
      "change": 3.829998,
      "volume": 1132353,
      "marketCap": 4145959168
    },
    {
      "symbol": "SMG",
      "shortName": "Scotts Miracle-Gro Company (The",
      "price": 74.83,
      "changePct": 10.060308,
      "change": 6.840004,
      "volume": 422691,
      "marketCap": 4353754624
    },
    {
      "symbol": "MATX",
      "shortName": "Matson, Inc.",
      "price": 226.03,
      "changePct": 8.200098,
      "change": 17.130005,
      "volume": 119952,
      "marketCap": 6840409088
    },
    {
      "symbol": "DXCM",
      "shortName": "DexCom, Inc.",
      "price": 77.99,
      "changePct": 7.232221,
      "change": 5.2599945,
      "volume": 2312406,
      "marketCap": 30094233600
    },
    {
      "symbol": "ERIE",
      "shortName": "Erie Indemnity Company",
      "price": 225.145,
      "changePct": 7.114992,
      "change": 14.955002,
      "volume": 107311,
      "marketCap": 11772802048
    },
    {
      "symbol": "ARCB",
      "shortName": "ArcBest Corporation",
      "price": 157.81,
      "changePct": 7.011593,
      "change": 10.339996,
      "volume": 68872,
      "marketCap": 3513447168
    },
    {
      "symbol": "TFII",
      "shortName": "TFI International Inc.",
      "price": 156.3,
      "changePct": 6.886417,
      "change": 10.070007,
      "volume": 145537,
      "marketCap": 12845676544
    },
    {
      "symbol": "BCC",
      "shortName": "Boise Cascade, L.L.C.",
      "price": 81.17,
      "changePct": 6.8166866,
      "change": 5.1800003,
      "volume": 203776,
      "marketCap": 2856350720
    },
    {
      "symbol": "GT",
      "shortName": "The Goodyear Tire & Rubber Comp",
      "price": 7.185,
      "changePct": 6.6023765,
      "change": 0.44500017,
      "volume": 4999435,
      "marketCap": 2065246464
    },
    {
      "symbol": "NWL",
      "shortName": "Newell Brands Inc.",
      "price": 5.5,
      "changePct": 6.5891504,
      "change": 0.34000015,
      "volume": 2246394,
      "marketCap": 2337102848
    },
    {
      "symbol": "CTAS",
      "shortName": "Cintas Corporation",
      "price": 204.96,
      "changePct": 6.544686,
      "change": 12.590012,
      "volume": 914583,
      "marketCap": 82012061696
    },
    {
      "symbol": "IR",
      "shortName": "Ingersoll Rand Inc.",
      "price": 84.18,
      "changePct": 6.368462,
      "change": 5.040001,
      "volume": 2692324,
      "marketCap": 32942735360
    },
    {
      "symbol": "JBHT",
      "shortName": "J.B. Hunt Transport Services, I",
      "price": 293.73,
      "changePct": 6.3160605,
      "change": 17.450012,
      "volume": 970677,
      "marketCap": 27698505728
    },
    {
      "symbol": "HUBG",
      "shortName": "Hub Group, Inc.",
      "price": 50.765,
      "changePct": 6.203578,
      "change": 2.9650002,
      "volume": 319339,
      "marketCap": 3104457984
    },
    {
      "symbol": "RXO",
      "shortName": "RXO, Inc.",
      "price": 28.685,
      "changePct": 5.966013,
      "change": 1.6149998,
      "volume": 475329,
      "marketCap": 4730739200
    },
    {
      "symbol": "MAT",
      "shortName": "Mattel, Inc.",
      "price": 14.655,
      "changePct": 5.7359314,
      "change": 0.7950001,
      "volume": 2064446,
      "marketCap": 4258288384
    },
    {
      "symbol": "IMOS",
      "shortName": "ChipMOS TECHNOLOGIES INC.",
      "price": 72.54,
      "changePct": 5.6818204,
      "change": 3.9000015,
      "volume": 80591,
      "marketCap": 2522281472
    },
    {
      "symbol": "SNDR",
      "shortName": "Schneider National, Inc.",
      "price": 38.5,
      "changePct": 5.6531324,
      "change": 2.0600014,
      "volume": 242248,
      "marketCap": 6742285824
    },
    {
      "symbol": "BBWI",
      "shortName": "Bath & Body Works, Inc.",
      "price": 21.765,
      "changePct": 5.3484974,
      "change": 1.1049995,
      "volume": 1519926,
      "marketCap": 4386992640
    }
  ],
  "losers": [
    {
      "symbol": "CHRN",
      "shortName": "ChronoScale Holdings Corporatio",
      "price": 23.79,
      "changePct": -19.709747,
      "change": -5.8399982,
      "volume": 382101,
      "marketCap": 3454660864
    },
    {
      "symbol": "ASTS",
      "shortName": "AST SpaceMobile, Inc.",
      "price": 55.8293,
      "changePct": -15.805608,
      "change": -10.480698,
      "volume": 24305212,
      "marketCap": 21668722688
    },
    {
      "symbol": "AXTI",
      "shortName": "AXT Inc",
      "price": 46.77,
      "changePct": -12.448517,
      "change": -6.6499977,
      "volume": 3691295,
      "marketCap": 3059842304
    },
    {
      "symbol": "RKLB",
      "shortName": "Rocket Lab Corporation",
      "price": 68.005,
      "changePct": -10.754594,
      "change": -8.195,
      "volume": 12452505,
      "marketCap": 42490798080
    },
    {
      "symbol": "MXL",
      "shortName": "MaxLinear, Inc",
      "price": 79.9051,
      "changePct": -10.057293,
      "change": -8.934898,
      "volume": 1196585,
      "marketCap": 7155178496
    },
    {
      "symbol": "SNDK",
      "shortName": "Sandisk Corporation",
      "price": 1456.13,
      "changePct": -9.837152,
      "change": -158.87,
      "volume": 7052567,
      "marketCap": 215637950464
    },
    {
      "symbol": "UMC",
      "shortName": "United Microelectronics Corpora",
      "price": 22.475,
      "changePct": -9.811396,
      "change": -2.4449997,
      "volume": 7000383,
      "marketCap": 56396218368
    },
    {
      "symbol": "XE",
      "shortName": "X-Energy, Inc.",
      "price": 13.59,
      "changePct": -9.760958,
      "change": -1.4700003,
      "volume": 2837327,
      "marketCap": 3906564096
    },
    {
      "symbol": "PL",
      "shortName": "Planet Labs PBC",
      "price": 22.49,
      "changePct": -9.678715,
      "change": -2.4099998,
      "volume": 4664352,
      "marketCap": 8015492608
    },
    {
      "symbol": "BB",
      "shortName": "BlackBerry Limited",
      "price": 9.6101,
      "changePct": -9.67506,
      "change": -1.0299006,
      "volume": 11603145,
      "marketCap": 5632483328
    },
    {
      "symbol": "YSS",
      "shortName": "York Space Systems Inc.",
      "price": 17.415,
      "changePct": -9.62636,
      "change": -1.8549995,
      "volume": 332746,
      "marketCap": 2288296960
    },
    {
      "symbol": "SKHY",
      "shortName": "SK hynix Inc. - American Depos",
      "price": 159.603,
      "changePct": -9.552878,
      "change": -16.85701,
      "volume": 19719014,
      "marketCap": 1132949667840
    },
    {
      "symbol": "BE",
      "shortName": "Bloom Energy Corporation",
      "price": 216.58,
      "changePct": -9.524606,
      "change": -22.800003,
      "volume": 5980358,
      "marketCap": 61604855808
    },
    {
      "symbol": "PENG",
      "shortName": "Penguin Solutions, Inc.",
      "price": 65.93,
      "changePct": -9.498968,
      "change": -6.919998,
      "volume": 1189557,
      "marketCap": 3378431232
    },
    {
      "symbol": "GLW",
      "shortName": "Corning Incorporated",
      "price": 157.855,
      "changePct": -9.492822,
      "change": -16.555008,
      "volume": 7306486,
      "marketCap": 135855980544
    },
    {
      "symbol": "SLS",
      "shortName": "SELLAS Life Sciences Group, Inc",
      "price": 11.58,
      "changePct": -9.460516,
      "change": -1.21,
      "volume": 4053842,
      "marketCap": 2277005312
    },
    {
      "symbol": "NBIS",
      "shortName": "Nebius Group N.V.",
      "price": 180.9401,
      "changePct": -9.3077545,
      "change": -18.5699,
      "volume": 5604788,
      "marketCap": 45940363264
    },
    {
      "symbol": "NVTS",
      "shortName": "Navitas Semiconductor Corporati",
      "price": 12.065,
      "changePct": -9.08064,
      "change": -1.2050009,
      "volume": 5327076,
      "marketCap": 2938492416
    },
    {
      "symbol": "VICR",
      "shortName": "Vicor Corporation",
      "price": 237.0,
      "changePct": -8.916223,
      "change": -23.200012,
      "volume": 176430,
      "marketCap": 10802793472
    },
    {
      "symbol": "CRDO",
      "shortName": "Credo Technology Group Holding ",
      "price": 207.06,
      "changePct": -8.679548,
      "change": -19.680008,
      "volume": 2047646,
      "marketCap": 38612115456
    },
    {
      "symbol": "SMR",
      "shortName": "NuScale Power Corporation",
      "price": 7.645,
      "changePct": -8.5526285,
      "change": -0.7149997,
      "volume": 9290058,
      "marketCap": 2645978880
    },
    {
      "symbol": "OKLO",
      "shortName": "Oklo Inc.",
      "price": 41.81,
      "changePct": -8.492005,
      "change": -3.8799973,
      "volume": 3653010,
      "marketCap": 7274563584
    },
    {
      "symbol": "CIFR",
      "shortName": "Cipher Digital Inc.",
      "price": 18.195,
      "changePct": -8.429799,
      "change": -1.6750011,
      "volume": 7856208,
      "marketCap": 7442649600
    },
    {
      "symbol": "SEI",
      "shortName": "Solaris Energy Infrastructure, ",
      "price": 61.53,
      "changePct": -8.3010435,
      "change": -5.5699997,
      "volume": 695192,
      "marketCap": 5911669248
    },
    {
      "symbol": "AUGO",
      "shortName": "Aura Minerals Inc.",
      "price": 50.4,
      "changePct": -8.213437,
      "change": -4.5099983,
      "volume": 182023,
      "marketCap": 4208400128
    }
  ],
  "actives": [
    {
      "symbol": "SKHYV",
      "shortName": "SK hynix Inc. - American Deposi",
      "price": 168.01,
      "changePct": 0.0,
      "change": 168.01,
      "volume": 107674661,
      "marketCap": 1192627142656
    },
    {
      "symbol": "ATAI",
      "shortName": "AtaiBeckley Inc.",
      "price": 7.155,
      "changePct": 33.50131,
      "change": 1.7950001,
      "volume": 103771986,
      "marketCap": 2634232832
    },
    {
      "symbol": "NOK",
      "shortName": "Nokia Corporation Sponsored",
      "price": 10.395,
      "changePct": -7.6033754,
      "change": -0.85499954,
      "volume": 58205378,
      "marketCap": 58030444544
    },
    {
      "symbol": "NVDA",
      "shortName": "NVIDIA Corporation",
      "price": 205.975,
      "changePct": -3.0705853,
      "change": -6.524994,
      "volume": 37648318,
      "marketCap": 4988920659968
    },
    {
      "symbol": "NU",
      "shortName": "Nu Holdings Ltd.",
      "price": 13.785,
      "changePct": -0.68443996,
      "change": -0.09500027,
      "volume": 33793877,
      "marketCap": 66588229632
    },
    {
      "symbol": "INTC",
      "shortName": "Intel Corporation",
      "price": 98.54,
      "changePct": -4.320805,
      "change": -4.449997,
      "volume": 33189364,
      "marketCap": 495262040064
    },
    {
      "symbol": "OPEN",
      "shortName": "Opendoor Technologies Inc",
      "price": 4.665,
      "changePct": -1.79053,
      "change": -0.08500004,
      "volume": 32985772,
      "marketCap": 4500496384
    },
    {
      "symbol": "AAL",
      "shortName": "American Airlines Group, Inc.",
      "price": 15.795,
      "changePct": 1.0555876,
      "change": 0.16499996,
      "volume": 28246251,
      "marketCap": 10446578688
    },
    {
      "symbol": "ASTS",
      "shortName": "AST SpaceMobile, Inc.",
      "price": 55.82,
      "changePct": -15.819632,
      "change": -10.489998,
      "volume": 24305505,
      "marketCap": 21665114112
    },
    {
      "symbol": "ONDS",
      "shortName": "Ondas Inc",
      "price": 6.6,
      "changePct": -6.3829827,
      "change": -0.4500003,
      "volume": 24143390,
      "marketCap": 3760934656
    },
    {
      "symbol": "SPCX",
      "shortName": "Space Exploration Technologies ",
      "price": 133.87,
      "changePct": -1.0349739,
      "change": -1.4000092,
      "volume": 21289343,
      "marketCap": 1763628285952
    },
    {
      "symbol": "SKHY",
      "shortName": "SK hynix Inc. - American Depos",
      "price": 159.807,
      "changePct": -9.437266,
      "change": -16.653,
      "volume": 19724556,
      "marketCap": 1134397882368
    },
    {
      "symbol": "PLUG",
      "shortName": "Plug Power, Inc.",
      "price": 2.175,
      "changePct": -1.5837142,
      "change": -0.035000086,
      "volume": 18672090,
      "marketCap": 3034275072
    },
    {
      "symbol": "LCID",
      "shortName": "Lucid Group, Inc.",
      "price": 6.6994,
      "changePct": 12.607675,
      "change": 0.74940014,
      "volume": 17973305,
      "marketCap": 2614486272
    },
    {
      "symbol": "MU",
      "shortName": "Micron Technology, Inc.",
      "price": 852.99,
      "changePct": -5.67192,
      "change": -51.29004,
      "volume": 17045258,
      "marketCap": 963361046528
    },
    {
      "symbol": "AAPL",
      "shortName": "Apple Inc.",
      "price": 330.37,
      "changePct": 0.87633437,
      "change": 2.869995,
      "volume": 16695146,
      "marketCap": 4852261847040
    },
    {
      "symbol": "SOFI",
      "shortName": "SoFi Technologies, Inc.",
      "price": 17.665,
      "changePct": -1.1471735,
      "change": -0.20499992,
      "volume": 16295136,
      "marketCap": 22659624960
    },
    {
      "symbol": "IREN",
      "shortName": "IREN LIMITED",
      "price": 35.4862,
      "changePct": -7.2983294,
      "change": -2.7938004,
      "volume": 15961779,
      "marketCap": 12682010624
    },
    {
      "symbol": "ORCL",
      "shortName": "Oracle Corporation",
      "price": 127.09,
      "changePct": -4.076863,
      "change": -5.400009,
      "volume": 15942414,
      "marketCap": 366079049728
    },
    {
      "symbol": "CPRX",
      "shortName": "Catalyst Pharmaceuticals, Inc.",
      "price": 31.49,
      "changePct": 0.0,
      "change": 0.0,
      "volume": 15513864,
      "marketCap": 3854925568
    },
    {
      "symbol": "T",
      "shortName": "AT&T Inc.",
      "price": 21.915,
      "changePct": 2.2631853,
      "change": 0.4850006,
      "volume": 15088382,
      "marketCap": 152272846848
    },
    {
      "symbol": "PATH",
      "shortName": "UiPath, Inc.",
      "price": 11.775,
      "changePct": -1.4641058,
      "change": -0.17500019,
      "volume": 14485088,
      "marketCap": 6100866048
    },
    {
      "symbol": "IOVA",
      "shortName": "Iovance Biotherapeutics, Inc.",
      "price": 4.9221,
      "changePct": 3.8434813,
      "change": 0.1821003,
      "volume": 13843309,
      "marketCap": 2197729536
    },
    {
      "symbol": "MARA",
      "shortName": "MARA Holdings, Inc.",
      "price": 11.635,
      "changePct": -5.3295336,
      "change": -0.65499973,
      "volume": 13567229,
      "marketCap": 4436082176
    },
    {
      "symbol": "GRAB",
      "shortName": "Grab Holdings Limited",
      "price": 3.695,
      "changePct": -3.2722514,
      "change": -0.125,
      "volume": 13506071,
      "marketCap": 15112549376
    }
  ]
}